{
  "fetchDate": "2026-07-12",
  "updatedAt": "2026-07-12T08:13:33+08:00",
  "inputs": {
    "lme": 3153,
    "usd": 32.225,
    "cny": 4.772,
    "baotai": 19200
  },
  "sources": {
    "lme": "westmetall",
    "fx": "bot-csv",
    "baotai": "baotai"
  },
  "items": [
    {
      "name": "鋁骨",
      "buy": 96.53,
      "quote": 91.53,
      "flag": null
    },
    {
      "name": "濁鋁骨",
      "buy": 81.08,
      "quote": 76.08,
      "flag": null
    },
    {
      "name": "6頭鋁屑",
      "buy": 66.04,
      "quote": 61.04,
      "flag": null
    },
    {
      "name": "混合鋁屑",
      "buy": 58.93,
      "quote": 53.93,
      "flag": null
    },
    {
      "name": "生鋁屑",
      "buy": 62.6,
      "quote": 57.6,
      "flag": null
    }
  ],
  "flags": {},
  "warnings": {}
}